Metadata-Version: 2.1
Name: odoo13-addon-ddmrp-sale
Version: 13.0.1.2.0
Summary: DDMRP integration with Sales app.
Home-page: https://github.com/OCA/ddmrp
Author: ForgeFlow, Odoo Community Association (OCA)
Author-email: support@odoo-community.org
License: LGPL-3
Platform: UNKNOWN
Classifier: Programming Language :: Python
Classifier: Framework :: Odoo
Classifier: Framework :: Odoo :: 13.0
Classifier: License :: OSI Approved :: GNU Lesser General Public License v3 (LGPLv3)
Classifier: Development Status :: 4 - Beta
Requires-Python: >=3.5
Requires-Dist: odoo13-addon-ddmrp
Requires-Dist: odoo13-addon-ddmrp-exclude-moves-adu-calc
Requires-Dist: odoo13-addon-sale-order-line-date
Requires-Dist: odoo (<13.1dev,>=13.0a)
